llama_index/storage/docstore/firestore/__init__.py
llama_index/storage/docstore/firestore/base.py
llama_index_storage_docstore_firestore-0.4.1.dist-info/METADATA
llama_index_storage_docstore_firestore-0.4.1.dist-info/WHEEL
llama_index_storage_docstore_firestore-0.4.1.dist-info/licenses/LICENSE
llama_index_storage_docstore_firestore-0.4.1.dist-info/RECORD
