Metadata-Version: 2.4
Name: llama-index-storage-docstore-firestore
Version: 0.4.1
Summary: llama-index docstore firestore integration
Author-email: Your Name <you@example.com>
License-Expression: MIT
License-File: LICENSE
Requires-Python: <4.0,>=3.9
Requires-Dist: llama-index-core<0.15,>=0.13.0
Requires-Dist: llama-index-storage-kvstore-firestore<0.6,>=0.5.0
